[
  {
    "resource": "google.com",
    "status": "Up",
    "timestamp": "2026-01-06T18:53:25.254031+00:00"
  },
  {
    "resource": "8.8.8.8",
    "status": "Up",
    "timestamp": "2026-01-06T18:53:25.258748+00:00"
  },
  {
    "resource": "github.com",
    "status": "Up",
    "timestamp": "2026-01-06T18:53:25.309742+00:00"
  },
  {
    "resource": "test.com",
    "status": "Down",
    "timestamp": "2026-01-06T18:53:25.314905+00:00"
  },
  {
    "resource": "google.com",
    "status": "Up",
    "timestamp": "2026-01-06T19:18:31.201599+00:00"
  },
  {
    "resource": "github.com",
    "status": "Up",
    "timestamp": "2026-01-06T19:18:31.239667+00:00"
  },
  {
    "resource": "cloudflare.com",
    "status": "Up",
    "timestamp": "2026-01-06T19:18:31.280420+00:00"
  },
  {
    "resource": "facebook.com",
    "status": "Up",
    "timestamp": "2026-01-06T19:18:31.323033+00:00"
  },
  {
    "resource": "amazon.com",
    "status": "Down",
    "timestamp": "2026-01-06T19:18:41.332110+00:00"
  },
  {
    "resource": "apple.com",
    "status": "Up",
    "timestamp": "2026-01-06T19:18:41.367451+00:00"
  },
  {
    "resource": "microsoft.com",
    "status": "Down",
    "timestamp": "2026-01-06T19:18:51.375810+00:00"
  },
  {
    "resource": "google.com",
    "status": "Up",
    "timestamp": "2026-01-06T20:09:18.521427+00:00"
  },
  {
    "resource": "github.com",
    "status": "Up",
    "timestamp": "2026-01-06T20:09:18.559001+00:00"
  },
  {
    "resource": "cloudflare.com",
    "status": "Up",
    "timestamp": "2026-01-06T20:09:18.596557+00:00"
  },
  {
    "resource": "facebook.com",
    "status": "Up",
    "timestamp": "2026-01-06T20:09:18.646219+00:00"
  },
  {
    "resource": "amazon.com",
    "status": "Down",
    "timestamp": "2026-01-06T20:09:28.654841+00:00"
  },
  {
    "resource": "apple.com",
    "status": "Up",
    "timestamp": "2026-01-06T20:09:28.683832+00:00"
  },
  {
    "resource": "microsoft.com",
    "status": "Down",
    "timestamp": "2026-01-06T20:09:38.691839+00:00"
  },
  {
    "resource": "uff.lightning.force.com",
    "status": "Down",
    "timestamp": "2026-01-06T21:09:37.393646+00:00"
  },
  {
    "resource": "ph12258.us-east-2.aws.snowflakecomputing.com",
    "status": "Down",
    "timestamp": "2026-01-06T21:09:47.405630+00:00"
  },
  {
    "resource": "ufadvancement.quickbase.com",
    "status": "Up",
    "timestamp": "2026-01-06T21:09:47.452600+00:00"
  },
  {
    "resource": "my.ufl.edu",
    "status": "Up",
    "timestamp": "2026-01-06T21:09:47.577867+00:00"
  },
  {
    "resource": "google.com",
    "status": "Up",
    "timestamp": "2026-01-06T21:09:47.594846+00:00"
  },
  {
    "resource": "github.com",
    "status": "Up",
    "timestamp": "2026-01-06T21:09:47.629340+00:00"
  }
]